{
  "topAssists": [
    {
      "playerId": 1000248,
      "playerName": "Cesc Fàbregas",
      "rank": 1,
      "teamId": 42,
      "teamName": "Arsenal",
      "value": 17
    },
    {
      "playerId": 1000141,
      "playerName": "Ashley Young",
      "rank": 2,
      "teamId": 66,
      "teamName": "Aston Villa",
      "value": 14
    },
    {
      "playerId": 1000519,
      "playerName": "Gareth Barry",
      "rank": 3,
      "teamId": 66,
      "teamName": "Aston Villa",
      "value": 10
    },
    {
      "playerId": 1001555,
      "playerName": "Wayne Rooney",
      "rank": 4,
      "teamId": 33,
      "teamName": "Manchester United",
      "value": 10
    },
    {
      "playerId": 1002949,
      "playerName": "Salomon Kalou",
      "rank": 5,
      "teamId": 49,
      "teamName": "Chelsea",
      "value": 10
    },
    {
      "playerId": 1002194,
      "playerName": "Dimitar Berbatov",
      "rank": 6,
      "teamId": 47,
      "teamName": "Tottenham Hotspur",
      "value": 9
    },
    {
      "playerId": 1002779,
      "playerName": "Nani",
      "rank": 7,
      "teamId": 33,
      "teamName": "Manchester United",
      "value": 9
    },
    {
      "playerId": 1002799,
      "playerName": "Nicky Shorey",
      "rank": 8,
      "teamId": 53,
      "teamName": "Reading",
      "value": 9
    },
    {
      "playerId": 1003729,
      "playerName": "Elano",
      "rank": 9,
      "teamId": 50,
      "teamName": "Manchester City",
      "value": 9
    },
    {
      "playerId": 1002150,
      "playerName": "David Bentley",
      "rank": 10,
      "teamId": 67,
      "teamName": "Blackburn Rovers",
      "value": 8
    }
  ],
  "topRedCards": [
    {
      "playerId": 1002893,
      "playerName": "Richard Dunne",
      "rank": 1,
      "teamId": 50,
      "teamName": "Manchester City",
      "value": 2
    },
    {
      "playerId": 1002942,
      "playerName": "Ryan Nelsen",
      "rank": 2,
      "teamId": 67,
      "teamName": "Blackburn Rovers",
      "value": 2
    },
    {
      "playerId": 1003048,
      "playerName": "Sulley Muntari",
      "rank": 3,
      "teamId": 1355,
      "teamName": "Portsmouth",
      "value": 2
    },
    {
      "playerId": 1000308,
      "playerName": "Cristiano Ronaldo",
      "rank": 4,
      "teamId": 33,
      "teamName": "Manchester United",
      "value": 1
    },
    {
      "playerId": 1001396,
      "playerName": "Scott Carson",
      "rank": 5,
      "teamId": 66,
      "teamName": "Aston Villa",
      "value": 1
    },
    {
      "playerId": 1001443,
      "playerName": "Stephen Ireland",
      "rank": 6,
      "teamId": 50,
      "teamName": "Manchester City",
      "value": 1
    },
    {
      "playerId": 1001931,
      "playerName": "Alan Smith",
      "rank": 7,
      "teamId": 34,
      "teamName": "Newcastle United",
      "value": 1
    },
    {
      "playerId": 1002003,
      "playerName": "Ashley Cole",
      "rank": 8,
      "teamId": 49,
      "teamName": "Chelsea",
      "value": 1
    },
    {
      "playerId": 1002043,
      "playerName": "Brett Emerton",
      "rank": 9,
      "teamId": 67,
      "teamName": "Blackburn Rovers",
      "value": 1
    },
    {
      "playerId": 1002053,
      "playerName": "Brynjar Gunnarsson",
      "rank": 10,
      "teamId": 53,
      "teamName": "Reading",
      "value": 1
    }
  ],
  "topScorers": [
    {
      "playerId": 1000308,
      "playerName": "Cristiano Ronaldo",
      "rank": 1,
      "teamId": 33,
      "teamName": "Manchester United",
      "value": 31
    },
    {
      "playerId": 1002242,
      "playerName": "Emmanuel Adebayor",
      "rank": 2,
      "teamId": 42,
      "teamName": "Arsenal",
      "value": 24
    },
    {
      "playerId": 1002272,
      "playerName": "Fernando Torres",
      "rank": 3,
      "teamId": 40,
      "teamName": "Liverpool",
      "value": 24
    },
    {
      "playerId": 1002924,
      "playerName": "Roque Santa Cruz",
      "rank": 4,
      "teamId": 67,
      "teamName": "Blackburn Rovers",
      "value": 19
    },
    {
      "playerId": 1002019,
      "playerName": "Benjani",
      "rank": 5,
      "teamId": 1355,
      "teamName": "Portsmouth",
      "value": 15
    },
    {
      "playerId": 1002194,
      "playerName": "Dimitar Berbatov",
      "rank": 6,
      "teamId": 47,
      "teamName": "Tottenham Hotspur",
      "value": 15
    },
    {
      "playerId": 1002903,
      "playerName": "Robbie Keane",
      "rank": 7,
      "teamId": 47,
      "teamName": "Tottenham Hotspur",
      "value": 15
    },
    {
      "playerId": 1003121,
      "playerName": "Yakubu",
      "rank": 8,
      "teamId": 45,
      "teamName": "Everton",
      "value": 15
    },
    {
      "playerId": 1002073,
      "playerName": "Carlos Tevez",
      "rank": 9,
      "teamId": 33,
      "teamName": "Manchester United",
      "value": 14
    },
    {
      "playerId": 1002471,
      "playerName": "John Carew",
      "rank": 10,
      "teamId": 66,
      "teamName": "Aston Villa",
      "value": 13
    }
  ],
  "topYellowCards": [
    {
      "playerId": 1004674,
      "playerName": "Nicky Butt",
      "rank": 1,
      "teamId": 34,
      "teamName": "Newcastle United",
      "value": 13
    },
    {
      "playerId": 1002228,
      "playerName": "El Hadji Diouf",
      "rank": 2,
      "teamId": 68,
      "teamName": "Bolton Wanderers",
      "value": 11
    },
    {
      "playerId": 1004555,
      "playerName": "Michael Brown",
      "rank": 3,
      "teamId": 61,
      "teamName": "Wigan Athletic",
      "value": 11
    },
    {
      "playerId": 1002093,
      "playerName": "Christopher Samba",
      "rank": 4,
      "teamId": 67,
      "teamName": "Blackburn Rovers",
      "value": 10
    },
    {
      "playerId": 1002563,
      "playerName": "Kevin Davies",
      "rank": 5,
      "teamId": 68,
      "teamName": "Bolton Wanderers",
      "value": 10
    },
    {
      "playerId": 1002567,
      "playerName": "Kevin Nolan",
      "rank": 6,
      "teamId": 68,
      "teamName": "Bolton Wanderers",
      "value": 10
    },
    {
      "playerId": 1004368,
      "playerName": "Liam Ridgewell",
      "rank": 7,
      "teamId": 54,
      "teamName": "Birmingham City",
      "value": 10
    },
    {
      "playerId": 1000248,
      "playerName": "Cesc Fàbregas",
      "rank": 8,
      "teamId": 42,
      "teamName": "Arsenal",
      "value": 9
    },
    {
      "playerId": 1001931,
      "playerName": "Alan Smith",
      "rank": 9,
      "teamId": 34,
      "teamName": "Newcastle United",
      "value": 9
    },
    {
      "playerId": 1002075,
      "playerName": "Carlton Cole",
      "rank": 10,
      "teamId": 48,
      "teamName": "West Ham United",
      "value": 9
    }
  ]
}
