[
  {
    "drawn": 4,
    "goalsAgainst": 22,
    "goalsDiff": 50,
    "goalsFor": 72,
    "lost": 5,
    "played": 38,
    "points": 91,
    "rank": 1,
    "teamId": 49,
    "teamName": "Chelsea",
    "won": 29
  },
  {
    "drawn": 8,
    "goalsAgainst": 34,
    "goalsDiff": 38,
    "goalsFor": 72,
    "lost": 5,
    "played": 38,
    "points": 83,
    "rank": 2,
    "teamId": 33,
    "teamName": "Manchester United",
    "won": 25
  },
  {
    "drawn": 7,
    "goalsAgainst": 25,
    "goalsDiff": 32,
    "goalsFor": 57,
    "lost": 6,
    "played": 38,
    "points": 82,
    "rank": 3,
    "teamId": 40,
    "teamName": "Liverpool",
    "won": 25
  },
  {
    "drawn": 7,
    "goalsAgainst": 31,
    "goalsDiff": 37,
    "goalsFor": 68,
    "lost": 11,
    "played": 38,
    "points": 67,
    "rank": 4,
    "teamId": 42,
    "teamName": "Arsenal",
    "won": 20
  },
  {
    "drawn": 11,
    "goalsAgainst": 38,
    "goalsDiff": 15,
    "goalsFor": 53,
    "lost": 9,
    "played": 38,
    "points": 65,
    "rank": 5,
    "teamId": 47,
    "teamName": "Tottenham Hotspur",
    "won": 18
  },
  {
    "drawn": 6,
    "goalsAgainst": 42,
    "goalsDiff": 9,
    "goalsFor": 51,
    "lost": 13,
    "played": 38,
    "points": 63,
    "rank": 6,
    "teamId": 67,
    "teamName": "Blackburn Rovers",
    "won": 19
  },
  {
    "drawn": 7,
    "goalsAgainst": 42,
    "goalsDiff": 5,
    "goalsFor": 47,
    "lost": 14,
    "played": 38,
    "points": 58,
    "rank": 7,
    "teamId": 34,
    "teamName": "Newcastle United",
    "won": 17
  },
  {
    "drawn": 11,
    "goalsAgainst": 41,
    "goalsDiff": 8,
    "goalsFor": 49,
    "lost": 12,
    "played": 38,
    "points": 56,
    "rank": 8,
    "teamId": 68,
    "teamName": "Bolton Wanderers",
    "won": 15
  },
  {
    "drawn": 7,
    "goalsAgainst": 55,
    "goalsDiff": -3,
    "goalsFor": 52,
    "lost": 15,
    "played": 38,
    "points": 55,
    "rank": 9,
    "teamId": 48,
    "teamName": "West Ham United",
    "won": 16
  },
  {
    "drawn": 6,
    "goalsAgainst": 52,
    "goalsDiff": -7,
    "goalsFor": 45,
    "lost": 17,
    "played": 38,
    "points": 51,
    "rank": 10,
    "teamId": 61,
    "teamName": "Wigan Athletic",
    "won": 15
  },
  {
    "drawn": 8,
    "goalsAgainst": 49,
    "goalsDiff": -15,
    "goalsFor": 34,
    "lost": 16,
    "played": 38,
    "points": 50,
    "rank": 11,
    "teamId": 45,
    "teamName": "Everton",
    "won": 14
  },
  {
    "drawn": 6,
    "goalsAgainst": 58,
    "goalsDiff": -10,
    "goalsFor": 48,
    "lost": 18,
    "played": 38,
    "points": 48,
    "rank": 12,
    "teamId": 36,
    "teamName": "Fulham",
    "won": 14
  },
  {
    "drawn": 8,
    "goalsAgainst": 55,
    "goalsDiff": -14,
    "goalsFor": 41,
    "lost": 17,
    "played": 38,
    "points": 47,
    "rank": 13,
    "teamId": 1335,
    "teamName": "Charlton Athletic",
    "won": 13
  },
  {
    "drawn": 9,
    "goalsAgainst": 58,
    "goalsDiff": -10,
    "goalsFor": 48,
    "lost": 17,
    "played": 38,
    "points": 45,
    "rank": 14,
    "teamId": 70,
    "teamName": "Middlesbrough",
    "won": 12
  },
  {
    "drawn": 4,
    "goalsAgainst": 48,
    "goalsDiff": -5,
    "goalsFor": 43,
    "lost": 21,
    "played": 38,
    "points": 43,
    "rank": 15,
    "teamId": 50,
    "teamName": "Manchester City",
    "won": 13
  },
  {
    "drawn": 12,
    "goalsAgainst": 55,
    "goalsDiff": -13,
    "goalsFor": 42,
    "lost": 16,
    "played": 38,
    "points": 42,
    "rank": 16,
    "teamId": 66,
    "teamName": "Aston Villa",
    "won": 10
  },
  {
    "drawn": 8,
    "goalsAgainst": 62,
    "goalsDiff": -25,
    "goalsFor": 37,
    "lost": 20,
    "played": 38,
    "points": 38,
    "rank": 17,
    "teamId": 1355,
    "teamName": "Portsmouth",
    "won": 10
  },
  {
    "drawn": 10,
    "goalsAgainst": 50,
    "goalsDiff": -22,
    "goalsFor": 28,
    "lost": 20,
    "played": 38,
    "points": 34,
    "rank": 18,
    "teamId": 54,
    "teamName": "Birmingham City",
    "won": 8
  },
  {
    "drawn": 9,
    "goalsAgainst": 58,
    "goalsDiff": -27,
    "goalsFor": 31,
    "lost": 22,
    "played": 38,
    "points": 30,
    "rank": 19,
    "teamId": 60,
    "teamName": "West Bromwich Albion",
    "won": 7
  },
  {
    "drawn": 6,
    "goalsAgainst": 69,
    "goalsDiff": -43,
    "goalsFor": 26,
    "lost": 29,
    "played": 38,
    "points": 15,
    "rank": 20,
    "teamId": 746,
    "teamName": "Sunderland",
    "won": 3
  }
]
